checker/__init__.py
checker/__main__.py
checker/exceptions.py
checker/py.typed
checker/actions/__init__.py
checker/actions/check.py
checker/actions/contributing.py
checker/actions/export.py
checker/actions/grade.py
checker/actions/grade_mr.py
checker/course/__init__.py
checker/course/config.py
checker/course/driver.py
checker/course/schedule.py
checker/executors/__init__.py
checker/executors/sandbox.py
checker/testers/__init__.py
checker/testers/cpp.py
checker/testers/make.py
checker/testers/python.py
checker/testers/tester.py
checker/utils/__init__.py
checker/utils/files.py
checker/utils/git.py
checker/utils/glab.py
checker/utils/manytask.py
checker/utils/print.py
checker/utils/template.py
manytask_checker-0.9.2.dist-info/METADATA
manytask_checker-0.9.2.dist-info/WHEEL
manytask_checker-0.9.2.dist-info/entry_points.txt
manytask_checker-0.9.2.dist-info/top_level.txt
manytask_checker-0.9.2.dist-info/RECORD
