Metadata-Version: 2.1
Name: manytask-checker
Version: 0.9.2
Summary: Students' solution checker
Author-email: Konstantin Chernyshev <kdchernyshev@gmail.com>
Project-URL: Source, https://github.com/yandexdataschool/checker
Classifier: Development Status :: 4 - Beta
Classifier: Typing :: Typed
Classifier: Intended Audience :: Education
Classifier: Topic :: Education
Classifier: Topic :: Education :: Testing
Classifier: Programming Language :: Python :: 3 :: Only
Classifier: Programming Language :: Python :: 3.8
Classifier: Programming Language :: Python :: 3.9
Classifier: Programming Language :: Python :: 3.10
Classifier: Programming Language :: Python :: 3.11
Classifier: Programming Language :: Python :: 3.12
Requires-Python: >=3.8
Requires-Dist: PyYAML <7.0.0,>=5.0.0
Requires-Dist: click <9.0,>=8.0
Requires-Dist: python-gitlab <4.0.0,>=3.0.0
Requires-Dist: requests <3.0.0,>=2.20.0
Requires-Dist: unshare <0.30,>=0.22 ; sys_platform != "darwin"
Provides-Extra: test
Requires-Dist: pytest <8.0.0,>=6.0.0 ; extra == 'test'
Requires-Dist: pytest-cov <5.0.0,>=4.0.0 ; extra == 'test'
Requires-Dist: pytest-mock <4.0.0,>=3.0.0 ; extra == 'test'
Requires-Dist: black ==23.11.0 ; extra == 'test'
Requires-Dist: mypy >=1.0.0 ; extra == 'test'
Requires-Dist: flake8 <7.0.0,>=4.0.0 ; extra == 'test'
Requires-Dist: isort <7.0.0,>=5.0.0 ; extra == 'test'
Requires-Dist: ruff ==0.1.5 ; extra == 'test'
Requires-Dist: types-requests <3.0.0,>=2.20.0 ; extra == 'test'
Requires-Dist: types-PyYAML <7.0.0,>=6.0.0 ; extra == 'test'
Requires-Dist: wheel >=0.40.0 ; extra == 'test'
